{
  "message" : {
    "Transactions": [
       {
        "accountNumber" : "202040-03333825",
        "date": "26/09/2023",
        "amount" : 100.00,
        "sign" : "cr",
        "currency" : "GBP",
        "description" : "credit amount paid by Lewis",
        "category" : "Transfer",
        "isHidden" : false,
        "merchantLogo" : "Barclays",
        "merchantName" : "AK",
        "type" : "Posted"
       },
       {
        "accountNumber" : "202040-03333825",
        "date": "26/09/2023",
        "amount" : 100.00,
        "sign" : "dr",
        "currency" : "GBP",
        "description" : "credit amount paid by Lewis",
        "category" : "Transfer",
        "isHidden" : false,
        "merchantLogo" : "Barclays",
        "merchantName" : "AK",
        "type" : "Posted"
       },
       {
        "accountNumber" : "202040-03333825",
        "date": "26/09/2023",
        "amount" : 100.00,
        "sign" : "cr",
        "currency" : "GBP",
        "description" : "credit amount paid by Lewis",
        "category" : "Transfer",
        "isHidden" : false,
        "merchantLogo" : "Barclays",
        "merchantName" : "AK",
        "type" : "Posted"
       },
       {
        "accountNumber" : "202040-03333825",
        "date": "26/09/2023",
        "amount" : 100.00,
        "sign" : "dr",
        "currency" : "GBP",
        "description" : "credit amount paid by Lewis",
        "category" : "Transfer",
        "isHidden" : false,
        "merchantLogo" : "Barclays",
        "merchantName" : "AK",
        "type" : "Posted"
       },
       {
        "accountNumber" : "202040-03333825",
        "date": "26/09/2023",
        "amount" : 100.00,
        "sign" : "dr",
        "currency" : "GBP",
        "description" : "credit amount paid by Lewis",
        "category" : "Transfer",
        "isHidden" : false,
        "merchantLogo" : "Barclays",
        "merchantName" : "AK",
        "type" : "Pending"
       },
       {
        "accountNumber" : "202040-03333825",
        "date": "26/09/2023",
        "amount" : 100.00,
        "sign" : "dr",
        "currency" : "GBP",
        "description" : "credit amount paid by Lewis",
        "category" : "Transfer",
        "isHidden" : false,
        "merchantLogo" : "Barclays",
        "merchantName" : "AK",
        "type" : "Posted"
       },
       {
        "accountNumber" : "202040-03333825",
        "date": "26/09/2023",
        "amount" : 100.00,
        "sign" : "dr",
        "currency" : "GBP",
        "description" : "credit amount paid by Lewis",
        "category" : "Transfer",
        "isHidden" : false,
        "merchantLogo" : "Barclays",
        "merchantName" : "AK",
        "type" : "Pending"
       }
    ]
 },
 "status":"success"
}
